{
  "routes": [
    {
      "from": 11,
      "branch": [
        {
          "to": 12,
          "text": "ブルータスと戦う",
          "next": 13
        },
        {
          "to": 15,
          "text": "ブルータスと和解する",
          "next": 16
        },
        {
          "to": 17,
          "text": "(最初から王国にいる)",
          "next": 18
        }
      ]
    },
    {
      "from": 16,
      "branch": [
        {
          "to": 10,
          "text": "邂逅へ",
          "next": 11
        }
      ]
    },
    {
      "from": 14,
      "branch": [
        {
          "to": 10,
          "text": "邂逅へ",
          "next": 11
        }
      ]
    },
    {
      "from": 14,
      "branch": [
        {
          "to": 10,
          "text": "邂逅へ",
          "next": 11
        }
      ]
    },
    {
      "from": 18,
      "branch": [
        {
          "to": 1,
          "text": "城下町へ",
          "next": 2
        },
        {
          "to": 19,
          "text": "近くにある棚を調べる",
          "next": 20
        }
      ]
    }
  ]
}